redblacktreepy/__init__.py
redblacktreepy-0.0.2.dist-info/METADATA
redblacktreepy-0.0.2.dist-info/WHEEL
redblacktreepy-0.0.2.dist-info/licenses/LICENSE
redblacktreepy-0.0.2.dist-info/RECORD
