Metadata-Version: 2.4
Name: redblacktreepy
Version: 0.0.2
Summary: A Red Black Tree implementation in python
Project-URL: Source, https://github.com/lincketheo/rbtreepy
Project-URL: Docs, https://github.com/lincketheo/rbtreepy
Author-email: Theo Lincke <lincketheo@gmail.com>
License: MIT
License-File: LICENSE
Requires-Python: >=3.9
